MEDfl/__init__.py
MEDfl/LearningManager/__init__.py
MEDfl/LearningManager/client.py
MEDfl/LearningManager/dynamicModal.py
MEDfl/LearningManager/federated_dataset.py
MEDfl/LearningManager/flpipeline.py
MEDfl/LearningManager/model.py
MEDfl/LearningManager/params.yaml
MEDfl/LearningManager/params_optimiser.py
MEDfl/LearningManager/plot.py
MEDfl/LearningManager/server.py
MEDfl/LearningManager/strategy.py
MEDfl/LearningManager/utils.py
MEDfl/NetManager/__init__.py
MEDfl/NetManager/database_connector.py
MEDfl/NetManager/dataset.py
MEDfl/NetManager/flsetup.py
MEDfl/NetManager/net_helper.py
MEDfl/NetManager/net_manager_queries.py
MEDfl/NetManager/network.py
MEDfl/NetManager/node.py
MEDfl/rw/__init__.py
MEDfl/rw/client.py
MEDfl/rw/model.py
MEDfl/rw/server.py
MEDfl/rw/strategy.py
MEDfl/scripts/__init__.py
MEDfl/scripts/base.py
MEDfl/scripts/create_db.py
alembic/__init__.py
alembic/env.py
MEDfl-2.0.5.dist-info/LICENSE
MEDfl-2.0.5.dist-info/METADATA
MEDfl-2.0.5.dist-info/WHEEL
MEDfl-2.0.5.dist-info/top_level.txt
MEDfl-2.0.5.dist-info/RECORD
